{"name":"closure","slug":"closure","count":1,"postlist":[{"title":" JavaScript 的静态作用域链与“动态”闭包链","slug":"javascript/8bd3b1ab2f","date":"2019-09-03T00:00:00.000Z","updated":"2021-06-17T11:25:09.047Z","comments":true,"path":"api/articles/javascript/8bd3b1ab2f.json","excerpt":"<p>读完本文会解答你以下疑问：</p>\n<ul>\n<li>静态作用域链和动态作用域链的区别</li>\n<li>为什么会有闭包</li>\n<li>闭包什么时候创建的</li>\n<li>[[scopes]] 属性是什么</li>\n<li>闭包保存什么内容</li>\n<li>闭包存储在哪</li>\n<li>为什么 eval 性能不好</li>\n<li>eval 什么情况下会创建闭包</li>\n</ul>\n<p>在 JavaScript 里面，函数、块、模块都可以形成作用域（一个存放变量的独立空间），他们之间可以相互嵌套，作用域之间会形成引用关系，这条链叫做作用域链。</p>\n<p>作用域链具体是什么样呢？</p>","keywords":null,"cover":"/images/72f12fc7e7164cc0af23f3e16f03bb06~tplv-k3u1fbpfcp-watermark.image.png","content":null,"text":"读完本文会解答你以下疑问：静态作用域链和动态作用域链的区别为什么会有闭包闭包什么时候创建的[[scopes]] 属性是什么闭包保存什么内容闭包存储在哪为什么 eval 性能不好eval 什么情况下会创建闭包在 JavaScript 里面，函数、块、模块都可以形成作用域（一个存放变","link":"","raw":null,"photos":[],"categories":[{"name":"javascript","slug":"javascript","count":21,"path":"api/categories/javascript.json"}],"tags":[{"name":"javascript","slug":"javascript","count":25,"path":"api/tags/javascript.json"},{"name":"closure","slug":"closure","count":1,"path":"api/tags/closure.json"}]}]}