{"sort":2,"title":" git 添加 ssh key","slug":"git/59a209dce6","date":"2019-01-24T00:00:00.000Z","updated":"2021-06-17T11:25:09.047Z","comments":true,"path":"api/articles/git/59a209dce6.json","photos":[],"link":"","excerpt":"  创建 SSH Keyssh-keygen -t rsa -C &quot;tangxiaomiemail@gmail.com&quot;cd ~/.sshcat id_rsa.pub如果一切顺利的话，可以在用户主目录里找到 .ssh 目录，里面有 id_rsa 和 id_rsa.pub 两个文件，这两个就是 SSH Key 的秘钥对，id_rsa 是私钥，不能泄露出去，id_rsa.pub 是公钥，可以放心地告诉任何人.","covers":null,"content":"<ul>\n<li>  创建 SSH Key<pre><code class=\"hljs bash\">ssh-keygen -t rsa -C <span class=\"hljs-string\">&quot;tangxiaomiemail@gmail.com&quot;</span>\n<span class=\"hljs-built_in\">cd</span> ~/.ssh\ncat id_rsa.pub</code></pre>\n\n</li>\n</ul>\n<p>如果一切顺利的话，可以在用户主目录里找到 .ssh 目录，里面有 <code>id_rsa</code> 和 <code>id_rsa.pub</code> 两个文件，这两个就是 SSH Key 的秘钥对，id_rsa 是私钥，不能泄露出去，id_rsa.pub 是公钥，可以放心地告诉任何人.</p>\n<a id=\"more\"></a>\n<h2 id=\"全局配置\"><a href=\"#全局配置\" class=\"headerlink\" title=\"全局配置\"></a>全局配置</h2><pre><code class=\"hljs bash\">git config --global user.name <span class=\"hljs-string\">&quot;tangxiaomi&quot;</span>\ngit config --global user.email <span class=\"hljs-string\">&quot;tangxiaomiemail@gmail.com&quot;</span></code></pre>\n\n<h2 id=\"非全局配置-删除-global\"><a href=\"#非全局配置-删除-global\" class=\"headerlink\" title=\"非全局配置 删除 --global\"></a>非全局配置 <code>删除 --global</code></h2><pre><code class=\"hljs bash\">git config  user.name <span class=\"hljs-string\">&quot;tangxiaomi&quot;</span>\ngit config  user.email <span class=\"hljs-string\">&quot;tangxiaomiemail@gmail.com&quot;</span></code></pre>\n\n<h2 id=\"查看配置\"><a href=\"#查看配置\" class=\"headerlink\" title=\"查看配置\"></a>查看配置</h2><pre><code class=\"hljs bash\">git config --global user.name\ngit config --global user.email</code></pre>\n\n<h2 id=\"取消全局配置\"><a href=\"#取消全局配置\" class=\"headerlink\" title=\"取消全局配置\"></a>取消全局配置</h2><pre><code class=\"hljs bash\">git config --global --<span class=\"hljs-built_in\">unset</span> user.name\ngit config --global --<span class=\"hljs-built_in\">unset</span> user.email\n\ngit config --global user.name    <span class=\"hljs-comment\">#(查看)全局配置账户是否已经移除</span>\ngit config --global user.email   <span class=\"hljs-comment\">#(查看)全局配置邮箱是否已经移除</span></code></pre>\n\n","prev":{"title":" git 常用命令","slug":"git/09dfcc188e"},"next":{"title":" Flex 布局教程：语法篇","slug":"css/457b24fe23"},"categories":[{"name":"git","slug":"git","count":6,"path":"api/categories/git.json"}],"tags":[{"name":"git","slug":"git","count":6,"path":"api/tags/git.json"}]}